string_analysis/__init__.py
string_analysis/string_analysis.py
string_analysis_MatheusAD-0.0.1.dist-info/LICENSE
string_analysis_MatheusAD-0.0.1.dist-info/METADATA
string_analysis_MatheusAD-0.0.1.dist-info/WHEEL
string_analysis_MatheusAD-0.0.1.dist-info/top_level.txt
string_analysis_MatheusAD-0.0.1.dist-info/RECORD
